{
    "markets": [
        {
            "id": "325884872",
            "eventId": "33984846",
            "sportId": "7",
            "leagueId": "84240",
            "name": "Shohei Ohtani Runs",
            "subcategoryId": "17844",
            "componentMapping": {
                "primary": 331,
                "fallback": 0
            },
            "marketType": {
                "id": "14463",
                "betOfferTypeId": 0,
                "name": "Runs (Batter) Milestones"
            },
            "subscriptionKey": "markets--1290250081",
            "sortOrder": 1,
            "tags": [
                "SGP",
                "YourBetEligible",
                "Cashout",
                "IgnoreSortOrderOnPush",
                "PlayerProps"
            ],
            "correlatedId": "33984846|14463|2:109098",
            "dynamicMetadata": {}
        },
        {
            "id": "325884557",
            "eventId": "33984846",
            "sportId": "7",
            "leagueId": "84240",
            "name": "Kyle Tucker Runs",
            "subcategoryId": "17844",
            "componentMapping": {
                "primary": 331,
                "fallback": 0
            },
            "marketType": {
                "id": "14463",
                "betOfferTypeId": 0,
                "name": "Runs (Batter) Milestones"
            },
            "subscriptionKey": "markets--1290250081",
            "sortOrder": 2,
            "tags": [
                "SGP",
                "YourBetEligible",
                "Cashout",
                "IgnoreSortOrderOnPush",
                "PlayerProps"
            ],
            "correlatedId": "33984846|14463|2:108752",
            "dynamicMetadata": {}
        },
        {
            "id": "325884489",
            "eventId": "33984846",
            "sportId": "7",
            "leagueId": "84240",
            "name": "Freddie Freeman Runs",
            "subcategoryId": "17844",
            "componentMapping": {
                "primary": 331,
                "fallback": 0
            },
            "marketType": {
                "id": "14463",
                "betOfferTypeId": 0,
                "name": "Runs (Batter) Milestones"
            },
            "subscriptionKey": "markets--1290250081",
            "sortOrder": 3,
            "tags": [
                "SGP",
                "YourBetEligible",
                "Cashout",
                "IgnoreSortOrderOnPush",
                "PlayerProps"
            ],
            "correlatedId": "33984846|14463|2:109045",
            "dynamicMetadata": {}
        },
        {
            "id": "325884492",
            "eventId": "33984846",
            "sportId": "7",
            "leagueId": "84240",
            "name": "Will Smith (LAD) Runs",
            "subcategoryId": "17844",
            "componentMapping": {
                "primary": 331,
                "fallback": 0
            },
            "marketType": {
                "id": "14463",
                "betOfferTypeId": 0,
                "name": "Runs (Batter) Milestones"
            },
            "subscriptionKey": "markets--1290250081",
            "sortOrder": 4,
            "tags": [
                "SGP",
                "YourBetEligible",
                "Cashout",
                "IgnoreSortOrderOnPush",
                "PlayerProps"
            ],
            "correlatedId": "33984846|14463|2:118805",
            "dynamicMetadata": {}
        },
        {
            "id": "325884753",
            "eventId": "33984846",
            "sportId": "7",
            "leagueId": "84240",
            "name": "Max Muncy (LAD) Runs",
            "subcategoryId": "17844",
            "componentMapping": {
                "primary": 331,
                "fallback": 0
            },
            "marketType": {
                "id": "14463",
                "betOfferTypeId": 0,
                "name": "Runs (Batter) Milestones"
            },
            "subscriptionKey": "markets--1290250081",
            "sortOrder": 5,
            "tags": [
                "SGP",
                "YourBetEligible",
                "Cashout",
                "IgnoreSortOrderOnPush",
                "PlayerProps"
            ],
            "correlatedId": "33984846|14463|2:109545",
            "dynamicMetadata": {}
        },
        {
            "id": "325884641",
            "eventId": "33984846",
            "sportId": "7",
            "leagueId": "84240",
            "name": "Teoscar Hernandez Runs",
            "subcategoryId": "17844",
            "componentMapping": {
                "primary": 331,
                "fallback": 0
            },
            "marketType": {
                "id": "14463",
                "betOfferTypeId": 0,
                "name": "Runs (Batter) Milestones"
            },
            "subscriptionKey": "markets--1290250081",
            "sortOrder": 6,
            "tags": [
                "SGP",
                "YourBetEligible",
                "Cashout",
                "IgnoreSortOrderOnPush",
                "PlayerProps"
            ],
            "correlatedId": "33984846|14463|2:108670",
            "dynamicMetadata": {}
        },
        {
            "id": "325884847",
            "eventId": "33984846",
            "sportId": "7",
            "leagueId": "84240",
            "name": "Francisco Lindor Runs",
            "subcategoryId": "17844",
            "componentMapping": {
                "primary": 331,
                "fallback": 0
            },
            "marketType": {
                "id": "14463",
                "betOfferTypeId": 0,
                "name": "Runs (Batter) Milestones"
            },
            "subscriptionKey": "markets--1290250081",
            "sortOrder": 7,
            "tags": [
                "SGP",
                "YourBetEligible",
                "Cashout",
                "IgnoreSortOrderOnPush",
                "PlayerProps"
            ],
            "correlatedId": "33984846|14463|2:108168",
            "dynamicMetadata": {}
        },
        {
            "id": "325884484",
            "eventId": "33984846",
            "sportId": "7",
            "leagueId": "84240",
            "name": "Andy Pages Runs",
            "subcategoryId": "17844",
            "componentMapping": {
                "primary": 331,
                "fallback": 0
            },
            "marketType": {
                "id": "14463",
                "betOfferTypeId": 0,
                "name": "Runs (Batter) Milestones"
            },
            "subscriptionKey": "markets--1290250081",
            "sortOrder": 8,
            "tags": [
                "SGP",
                "YourBetEligible",
                "Cashout",
                "IgnoreSortOrderOnPush",
                "PlayerProps"
            ],
            "correlatedId": "33984846|14463|2:160886",
            "dynamicMetadata": {}
        },
        {
            "id": "325884743",
            "eventId": "33984846",
            "sportId": "7",
            "leagueId": "84240",
            "name": "Hyeseong Kim Runs",
            "subcategoryId": "17844",
            "componentMapping": {
                "primary": 331,
                "fallback": 0
            },
            "marketType": {
                "id": "14463",
                "betOfferTypeId": 0,
                "name": "Runs (Batter) Milestones"
            },
            "subscriptionKey": "markets--1290250081",
            "sortOrder": 9,
            "tags": [
                "SGP",
                "YourBetEligible",
                "Cashout",
                "IgnoreSortOrderOnPush",
                "PlayerProps"
            ],
            "correlatedId": "33984846|14463|2:197300",
            "dynamicMetadata": {}
        },
        {
            "id": "325884678",
            "eventId": "33984846",
            "sportId": "7",
            "leagueId": "84240",
            "name": "Luis Robert Runs",
            "subcategoryId": "17844",
            "componentMapping": {
                "primary": 331,
                "fallback": 0
            },
            "marketType": {
                "id": "14463",
                "betOfferTypeId": 0,
                "name": "Runs (Batter) Milestones"
            },
            "subscriptionKey": "markets--1290250081",
            "sortOrder": 10,
            "tags": [
                "SGP",
                "YourBetEligible",
                "Cashout",
                "IgnoreSortOrderOnPush",
                "PlayerProps"
            ],
            "correlatedId": "33984846|14463|2:106248",
            "dynamicMetadata": {}
        },
        {
            "id": "325884763",
            "eventId": "33984846",
            "sportId": "7",
            "leagueId": "84240",
            "name": "Alex Freeland Runs",
            "subcategoryId": "17844",
            "componentMapping": {
                "primary": 331,
                "fallback": 0
            },
            "marketType": {
                "id": "14463",
                "betOfferTypeId": 0,
                "name": "Runs (Batter) Milestones"
            },
            "subscriptionKey": "markets--1290250081",
            "sortOrder": 11,
            "tags": [
                "SGP",
                "YourBetEligible",
                "Cashout",
                "IgnoreSortOrderOnPush",
                "PlayerProps"
            ],
            "correlatedId": "33984846|14463|2:155928",
            "dynamicMetadata": {}
        },
        {
            "id": "325884676",
            "eventId": "33984846",
            "sportId": "7",
            "leagueId": "84240",
            "name": "Francisco Alvarez Runs",
            "subcategoryId": "17844",
            "componentMapping": {
                "primary": 331,
                "fallback": 0
            },
            "marketType": {
                "id": "14463",
                "betOfferTypeId": 0,
                "name": "Runs (Batter) Milestones"
            },
            "subscriptionKey": "markets--1290250081",
            "sortOrder": 12,
            "tags": [
                "SGP",
                "YourBetEligible",
                "Cashout",
                "IgnoreSortOrderOnPush",
                "PlayerProps"
            ],
            "correlatedId": "33984846|14463|2:107686",
            "dynamicMetadata": {}
        },
        {
            "id": "325884768",
            "eventId": "33984846",
            "sportId": "7",
            "leagueId": "84240",
            "name": "Bo Bichette Runs",
            "subcategoryId": "17844",
            "componentMapping": {
                "primary": 331,
                "fallback": 0
            },
            "marketType": {
                "id": "14463",
                "betOfferTypeId": 0,
                "name": "Runs (Batter) Milestones"
            },
            "subscriptionKey": "markets--1290250081",
            "sortOrder": 13,
            "tags": [
                "SGP",
                "YourBetEligible",
                "Cashout",
                "IgnoreSortOrderOnPush",
                "PlayerProps"
            ],
            "correlatedId": "33984846|14463|2:108723",
            "dynamicMetadata": {}
        },
        {
            "id": "325884976",
            "eventId": "33984846",
            "sportId": "7",
            "leagueId": "84240",
            "name": "Jorge Polanco Runs",
            "subcategoryId": "17844",
            "componentMapping": {
                "primary": 331,
                "fallback": 0
            },
            "marketType": {
                "id": "14463",
                "betOfferTypeId": 0,
                "name": "Runs (Batter) Milestones"
            },
            "subscriptionKey": "markets--1290250081",
            "sortOrder": 14,
            "tags": [
                "SGP",
                "YourBetEligible",
                "Cashout",
                "IgnoreSortOrderOnPush",
                "PlayerProps"
            ],
            "correlatedId": "33984846|14463|2:109186",
            "dynamicMetadata": {}
        },
        {
            "id": "325884621",
            "eventId": "33984846",
            "sportId": "7",
            "leagueId": "84240",
            "name": "Marcus Semien Runs",
            "subcategoryId": "17844",
            "componentMapping": {
                "primary": 331,
                "fallback": 0
            },
            "marketType": {
                "id": "14463",
                "betOfferTypeId": 0,
                "name": "Runs (Batter) Milestones"
            },
            "subscriptionKey": "markets--1290250081",
            "sortOrder": 15,
            "tags": [
                "SGP",
                "YourBetEligible",
                "Cashout",
                "IgnoreSortOrderOnPush",
                "PlayerProps"
            ],
            "correlatedId": "33984846|14463|2:109475",
            "dynamicMetadata": {}
        },
        {
            "id": "325884675",
            "eventId": "33984846",
            "sportId": "7",
            "leagueId": "84240",
            "name": "Brett Baty Runs",
            "subcategoryId": "17844",
            "componentMapping": {
                "primary": 331,
                "fallback": 0
            },
            "marketType": {
                "id": "14463",
                "betOfferTypeId": 0,
                "name": "Runs (Batter) Milestones"
            },
            "subscriptionKey": "markets--1290250081",
            "sortOrder": 16,
            "tags": [
                "SGP",
                "YourBetEligible",
                "Cashout",
                "IgnoreSortOrderOnPush",
                "PlayerProps"
            ],
            "correlatedId": "33984846|14463|2:106038",
            "dynamicMetadata": {}
        },
        {
            "id": "326166724",
            "eventId": "33984846",
            "sportId": "7",
            "leagueId": "84240",
            "name": "Mark Vientos Runs",
            "subcategoryId": "17844",
            "componentMapping": {
                "primary": 331,
                "fallback": 0
            },
            "marketType": {
                "id": "14463",
                "betOfferTypeId": 0,
                "name": "Runs (Batter) Milestones"
            },
            "subscriptionKey": "markets--1290250081",
            "sortOrder": 17,
            "tags": [
                "SGP",
                "YourBetEligible",
                "Cashout",
                "IgnoreSortOrderOnPush",
                "PlayerProps"
            ],
            "correlatedId": "33984846|14463|2:107678",
            "dynamicMetadata": {}
        },
        {
            "id": "325884886",
            "eventId": "33984846",
            "sportId": "7",
            "leagueId": "84240",
            "name": "Carson Benge Runs",
            "subcategoryId": "17844",
            "componentMapping": {
                "primary": 331,
                "fallback": 0
            },
            "marketType": {
                "id": "14463",
                "betOfferTypeId": 0,
                "name": "Runs (Batter) Milestones"
            },
            "subscriptionKey": "markets--1290250081",
            "sortOrder": 18,
            "tags": [
                "SGP",
                "YourBetEligible",
                "Cashout",
                "IgnoreSortOrderOnPush",
                "PlayerProps"
            ],
            "correlatedId": "33984846|14463|2:229324",
            "dynamicMetadata": {}
        }
    ],
    "selections": [
        {
            "id": "0QA325884484#565675235_13L84240Q11236389728Q20",
            "marketId": "325884484",
            "label": "1\u002B",
            "displayOdds": {
                "american": "\u002B148",
                "decimal": "2.48",
                "fractional": "37/25"
            },
            "trueOdds": 2.48,
            "participants": [
                {
                    "id": "459808",
                    "name": "Andy Pages",
                    "type": "Player",
                    "seoIdentifier": "Andy Pages",
                    "statistic": {
                        "prefix": "R",
                        "value": 9
                    },
                    "venueRole": "HomePlayer",
                    "isNationalTeam": false
                }
            ],
            "sortOrder": 24835,
            "tags": [
                "MostBalancedOdds",
                "SGP",
                "MostBalancedGlobalProbability"
            ],
            "metadata": {},
            "milestoneValue": 1
        },
        {
            "id": "0QA325884484#565675243_13L84240Q1355474852Q20",
            "marketId": "325884484",
            "label": "2\u002B",
            "displayOdds": {
                "american": "\u002B960",
                "decimal": "10.60",
                "fractional": "48/5"
            },
            "trueOdds": 10.6,
            "participants": [
                {
                    "id": "459808",
                    "name": "Andy Pages",
                    "type": "Player",
                    "seoIdentifier": "Andy Pages",
                    "statistic": {
                        "prefix": "R",
                        "value": 9
                    },
                    "venueRole": "HomePlayer",
                    "isNationalTeam": false
                }
            ],
            "sortOrder": 106043,
            "tags": [
                "SGP"
            ],
            "metadata": {},
            "milestoneValue": 2
        },
        {
            "id": "0QA325884489#565675286_13L84240Q11236389728Q20",
            "marketId": "325884489",
            "label": "1\u002B",
            "displayOdds": {
                "american": "\u002B109",
                "decimal": "2.09",
                "fractional": "109/100"
            },
            "trueOdds": 2.09,
            "participants": [
                {
                    "id": "32190",
                    "name": "Freddie Freeman",
                    "type": "Player",
                    "seoIdentifier": "Freddie Freeman",
                    "statistic": {
                        "prefix": "R",
                        "value": 8
                    },
                    "venueRole": "HomePlayer",
                    "isNationalTeam": false
                }
            ],
            "sortOrder": 20986,
            "tags": [
                "MostBalancedOdds",
                "SGP",
                "MostBalancedGlobalProbability"
            ],
            "metadata": {},
            "milestoneValue": 1
        },
        {
            "id": "0QA325884489#565675289_13L84240Q1355474852Q20",
            "marketId": "325884489",
            "label": "2\u002B",
            "displayOdds": {
                "american": "\u002B650",
                "decimal": "7.50",
                "fractional": "13/2"
            },
            "trueOdds": 7.5,
            "participants": [
                {
                    "id": "32190",
                    "name": "Freddie Freeman",
                    "type": "Player",
                    "seoIdentifier": "Freddie Freeman",
                    "statistic": {
                        "prefix": "R",
                        "value": 8
                    },
                    "venueRole": "HomePlayer",
                    "isNationalTeam": false
                }
            ],
            "sortOrder": 75089,
            "tags": [
                "SGP"
            ],
            "metadata": {},
            "milestoneValue": 2
        },
        {
            "id": "0QA325884492#565675275_13L84240Q11236389728Q20",
            "marketId": "325884492",
            "label": "1\u002B",
            "displayOdds": {
                "american": "\u002B113",
                "decimal": "2.13",
                "fractional": "113/100"
            },
            "trueOdds": 2.13,
            "participants": [
                {
                    "id": "32725",
                    "name": "Will Smith (LAD)",
                    "type": "Player",
                    "seoIdentifier": "Will Smith",
                    "statistic": {
                        "prefix": "R",
                        "value": 8
                    },
                    "venueRole": "HomePlayer",
                    "isNationalTeam": false
                }
            ],
            "sortOrder": 21375,
            "tags": [
                "MostBalancedOdds",
                "SGP",
                "MostBalancedGlobalProbability"
            ],
            "metadata": {},
            "milestoneValue": 1
        },
        {
            "id": "0QA325884492#565675282_13L84240Q1355474852Q20",
            "marketId": "325884492",
            "label": "2\u002B",
            "displayOdds": {
                "american": "\u002B650",
                "decimal": "7.50",
                "fractional": "13/2"
            },
            "trueOdds": 7.5,
            "participants": [
                {
                    "id": "32725",
                    "name": "Will Smith (LAD)",
                    "type": "Player",
                    "seoIdentifier": "Will Smith",
                    "statistic": {
                        "prefix": "R",
                        "value": 8
                    },
                    "venueRole": "HomePlayer",
                    "isNationalTeam": false
                }
            ],
            "sortOrder": 75082,
            "tags": [
                "SGP"
            ],
            "metadata": {},
            "milestoneValue": 2
        },
        {
            "id": "0QA325884557#565675311_13L84240Q11236389728Q20",
            "marketId": "325884557",
            "label": "1\u002B",
            "displayOdds": {
                "american": "\u002B104",
                "decimal": "2.04",
                "fractional": "26/25"
            },
            "trueOdds": 2.04,
            "participants": [
                {
                    "id": "32010",
                    "name": "Kyle Tucker",
                    "type": "Player",
                    "seoIdentifier": "Kyle Tucker",
                    "statistic": {
                        "prefix": "R",
                        "value": 12
                    },
                    "venueRole": "HomePlayer",
                    "isNationalTeam": false
                }
            ],
            "sortOrder": 20411,
            "tags": [
                "MostBalancedOdds",
                "SGP",
                "MostBalancedGlobalProbability"
            ],
            "metadata": {},
            "milestoneValue": 1
        },
        {
            "id": "0QA325884557#565675325_13L84240Q1355474852Q20",
            "marketId": "325884557",
            "label": "2\u002B",
            "displayOdds": {
                "american": "\u002B600",
                "decimal": "7.00",
                "fractional": "6/1"
            },
            "trueOdds": 7,
            "participants": [
                {
                    "id": "32010",
                    "name": "Kyle Tucker",
                    "type": "Player",
                    "seoIdentifier": "Kyle Tucker",
                    "statistic": {
                        "prefix": "R",
                        "value": 12
                    },
                    "venueRole": "HomePlayer",
                    "isNationalTeam": false
                }
            ],
            "sortOrder": 70025,
            "tags": [
                "SGP"
            ],
            "metadata": {},
            "milestoneValue": 2
        },
        {
            "id": "0QA325884621#565675404_13L84240Q11236389728Q20",
            "marketId": "325884621",
            "label": "1\u002B",
            "displayOdds": {
                "american": "\u002B207",
                "decimal": "3.07",
                "fractional": "207/100"
            },
            "trueOdds": 3.07,
            "participants": [
                {
                    "id": "32620",
                    "name": "Marcus Semien",
                    "type": "Player",
                    "seoIdentifier": "Marcus Semien",
                    "statistic": {
                        "prefix": "R",
                        "value": 2
                    },
                    "venueRole": "AwayPlayer",
                    "isNationalTeam": false
                }
            ],
            "sortOrder": 30704,
            "tags": [
                "MostBalancedOdds",
                "SGP",
                "MostBalancedGlobalProbability"
            ],
            "metadata": {},
            "milestoneValue": 1
        },
        {
            "id": "0QA325884641#565675478_13L84240Q11236389728Q20",
            "marketId": "325884641",
            "label": "1\u002B",
            "displayOdds": {
                "american": "\u002B138",
                "decimal": "2.38",
                "fractional": "69/50"
            },
            "trueOdds": 2.38,
            "participants": [
                {
                    "id": "31969",
                    "name": "Teoscar Hernandez",
                    "type": "Player",
                    "seoIdentifier": "Teoscar Hernandez",
                    "statistic": {
                        "prefix": "R",
                        "value": 10
                    },
                    "venueRole": "HomePlayer",
                    "isNationalTeam": false
                }
            ],
            "sortOrder": 23878,
            "tags": [
                "MostBalancedOdds",
                "SGP",
                "MostBalancedGlobalProbability"
            ],
            "metadata": {},
            "milestoneValue": 1
        },
        {
            "id": "0QA325884641#565675494_13L84240Q1355474852Q20",
            "marketId": "325884641",
            "label": "2\u002B",
            "displayOdds": {
                "american": "\u002B860",
                "decimal": "9.60",
                "fractional": "43/5"
            },
            "trueOdds": 9.6,
            "participants": [
                {
                    "id": "31969",
                    "name": "Teoscar Hernandez",
                    "type": "Player",
                    "seoIdentifier": "Teoscar Hernandez",
                    "statistic": {
                        "prefix": "R",
                        "value": 10
                    },
                    "venueRole": "HomePlayer",
                    "isNationalTeam": false
                }
            ],
            "sortOrder": 96094,
            "tags": [
                "SGP"
            ],
            "metadata": {},
            "milestoneValue": 2
        },
        {
            "id": "0QA325884675#565675864_13L84240Q11236389728Q20",
            "marketId": "325884675",
            "label": "1\u002B",
            "displayOdds": {
                "american": "\u002B211",
                "decimal": "3.11",
                "fractional": "211/100"
            },
            "trueOdds": 3.11,
            "participants": [
                {
                    "id": "459845",
                    "name": "Brett Baty",
                    "type": "Player",
                    "seoIdentifier": "Brett Baty",
                    "statistic": {
                        "prefix": "R",
                        "value": 6
                    },
                    "venueRole": "AwayPlayer",
                    "isNationalTeam": false
                }
            ],
            "sortOrder": 31164,
            "tags": [
                "MostBalancedOdds",
                "SGP",
                "MostBalancedGlobalProbability"
            ],
            "metadata": {},
            "milestoneValue": 1
        },
        {
            "id": "0QA325884676#565676038_13L84240Q11236389728Q20",
            "marketId": "325884676",
            "label": "1\u002B",
            "displayOdds": {
                "american": "\u002B178",
                "decimal": "2.78",
                "fractional": "89/50"
            },
            "trueOdds": 2.78,
            "participants": [
                {
                    "id": "112068",
                    "name": "Francisco Alvarez",
                    "type": "Player",
                    "seoIdentifier": "Francisco Alvarez",
                    "statistic": {
                        "prefix": "R",
                        "value": 7
                    },
                    "venueRole": "AwayPlayer",
                    "isNationalTeam": false
                }
            ],
            "sortOrder": 27837,
            "tags": [
                "MostBalancedOdds",
                "SGP",
                "MostBalancedGlobalProbability"
            ],
            "metadata": {},
            "milestoneValue": 1
        },
        {
            "id": "0QA325884676#565676144_13L84240Q1355474852Q20",
            "marketId": "325884676",
            "label": "2\u002B",
            "displayOdds": {
                "american": "\u002B1160",
                "decimal": "12.60",
                "fractional": "58/5"
            },
            "trueOdds": 12.6,
            "participants": [
                {
                    "id": "112068",
                    "name": "Francisco Alvarez",
                    "type": "Player",
                    "seoIdentifier": "Francisco Alvarez",
                    "statistic": {
                        "prefix": "R",
                        "value": 7
                    },
                    "venueRole": "AwayPlayer",
                    "isNationalTeam": false
                }
            ],
            "sortOrder": 126044,
            "tags": [
                "SGP"
            ],
            "metadata": {},
            "milestoneValue": 2
        },
        {
            "id": "0QA325884678#565675578_13L84240Q11236389728Q20",
            "marketId": "325884678",
            "label": "1\u002B",
            "displayOdds": {
                "american": "\u002B166",
                "decimal": "2.66",
                "fractional": "83/50"
            },
            "trueOdds": 2.66,
            "participants": [
                {
                    "id": "110692",
                    "name": "Luis Robert",
                    "type": "Player",
                    "seoIdentifier": "Luis Robert Jr.",
                    "statistic": {
                        "prefix": "R",
                        "value": 9
                    },
                    "venueRole": "AwayPlayer",
                    "isNationalTeam": false
                }
            ],
            "sortOrder": 26678,
            "tags": [
                "MostBalancedOdds",
                "SGP",
                "MostBalancedGlobalProbability"
            ],
            "metadata": {},
            "milestoneValue": 1
        },
        {
            "id": "0QA325884678#565675595_13L84240Q1355474852Q20",
            "marketId": "325884678",
            "label": "2\u002B",
            "displayOdds": {
                "american": "\u002B1040",
                "decimal": "11.40",
                "fractional": "52/5"
            },
            "trueOdds": 11.4,
            "participants": [
                {
                    "id": "110692",
                    "name": "Luis Robert",
                    "type": "Player",
                    "seoIdentifier": "Luis Robert Jr.",
                    "statistic": {
                        "prefix": "R",
                        "value": 9
                    },
                    "venueRole": "AwayPlayer",
                    "isNationalTeam": false
                }
            ],
            "sortOrder": 114095,
            "tags": [
                "SGP"
            ],
            "metadata": {},
            "milestoneValue": 2
        },
        {
            "id": "0QA325884743#565675920_13L84240Q11236389728Q20",
            "marketId": "325884743",
            "label": "1\u002B",
            "displayOdds": {
                "american": "\u002B159",
                "decimal": "2.59",
                "fractional": "159/100"
            },
            "trueOdds": 2.59,
            "participants": [
                {
                    "id": "486318",
                    "name": "Hyeseong Kim",
                    "type": "Player",
                    "seoIdentifier": "Hyeseong Kim",
                    "statistic": {
                        "prefix": "R",
                        "value": 3
                    },
                    "venueRole": "HomePlayer",
                    "isNationalTeam": false
                }
            ],
            "sortOrder": 25920,
            "tags": [
                "MostBalancedOdds",
                "SGP",
                "MostBalancedGlobalProbability"
            ],
            "metadata": {},
            "milestoneValue": 1
        },
        {
            "id": "0QA325884743#565676004_13L84240Q1355474852Q20",
            "marketId": "325884743",
            "label": "2\u002B",
            "displayOdds": {
                "american": "\u002B1020",
                "decimal": "11.20",
                "fractional": "51/5"
            },
            "trueOdds": 11.2,
            "participants": [
                {
                    "id": "486318",
                    "name": "Hyeseong Kim",
                    "type": "Player",
                    "seoIdentifier": "Hyeseong Kim",
                    "statistic": {
                        "prefix": "R",
                        "value": 3
                    },
                    "venueRole": "HomePlayer",
                    "isNationalTeam": false
                }
            ],
            "sortOrder": 112004,
            "tags": [
                "SGP"
            ],
            "metadata": {},
            "milestoneValue": 2
        },
        {
            "id": "0QA325884753#565675696_13L84240Q11236389728Q20",
            "marketId": "325884753",
            "label": "1\u002B",
            "displayOdds": {
                "american": "\u002B118",
                "decimal": "2.18",
                "fractional": "59/50"
            },
            "trueOdds": 2.18,
            "participants": [
                {
                    "id": "32690",
                    "name": "Max Muncy (LAD)",
                    "type": "Player",
                    "seoIdentifier": "Max Muncy",
                    "statistic": {
                        "prefix": "R",
                        "value": 11
                    },
                    "venueRole": "HomePlayer",
                    "isNationalTeam": false
                }
            ],
            "sortOrder": 21896,
            "tags": [
                "MostBalancedOdds",
                "SGP",
                "MostBalancedGlobalProbability"
            ],
            "metadata": {},
            "milestoneValue": 1
        },
        {
            "id": "0QA325884753#565675748_13L84240Q1355474852Q20",
            "marketId": "325884753",
            "label": "2\u002B",
            "displayOdds": {
                "american": "\u002B730",
                "decimal": "8.30",
                "fractional": "73/10"
            },
            "trueOdds": 8.3,
            "participants": [
                {
                    "id": "32690",
                    "name": "Max Muncy (LAD)",
                    "type": "Player",
                    "seoIdentifier": "Max Muncy",
                    "statistic": {
                        "prefix": "R",
                        "value": 11
                    },
                    "venueRole": "HomePlayer",
                    "isNationalTeam": false
                }
            ],
            "sortOrder": 83048,
            "tags": [
                "SGP"
            ],
            "metadata": {},
            "milestoneValue": 2
        },
        {
            "id": "0QA325884763#565675694_13L84240Q11236389728Q20",
            "marketId": "325884763",
            "label": "1\u002B",
            "displayOdds": {
                "american": "\u002B162",
                "decimal": "2.62",
                "fractional": "81/50"
            },
            "trueOdds": 2.62,
            "participants": [
                {
                    "id": "701865",
                    "name": "Alex Freeland",
                    "type": "Player",
                    "seoIdentifier": "Alex Freeland",
                    "statistic": {
                        "prefix": "R",
                        "value": 5
                    },
                    "venueRole": "HomePlayer",
                    "isNationalTeam": false
                }
            ],
            "sortOrder": 26294,
            "tags": [
                "MostBalancedOdds",
                "SGP",
                "MostBalancedGlobalProbability"
            ],
            "metadata": {},
            "milestoneValue": 1
        },
        {
            "id": "0QA325884763#565675746_13L84240Q1355474852Q20",
            "marketId": "325884763",
            "label": "2\u002B",
            "displayOdds": {
                "american": "\u002B1100",
                "decimal": "12.00",
                "fractional": "11/1"
            },
            "trueOdds": 12,
            "participants": [
                {
                    "id": "701865",
                    "name": "Alex Freeland",
                    "type": "Player",
                    "seoIdentifier": "Alex Freeland",
                    "statistic": {
                        "prefix": "R",
                        "value": 5
                    },
                    "venueRole": "HomePlayer",
                    "isNationalTeam": false
                }
            ],
            "sortOrder": 120046,
            "tags": [
                "SGP"
            ],
            "metadata": {},
            "milestoneValue": 2
        },
        {
            "id": "0QA325884768#565676323_13L84240Q11236389728Q20",
            "marketId": "325884768",
            "label": "1\u002B",
            "displayOdds": {
                "american": "\u002B193",
                "decimal": "2.93",
                "fractional": "193/100"
            },
            "trueOdds": 2.93,
            "participants": [
                {
                    "id": "31996",
                    "name": "Bo Bichette",
                    "type": "Player",
                    "seoIdentifier": "Bo Bichette",
                    "statistic": {
                        "prefix": "R",
                        "value": 6
                    },
                    "venueRole": "AwayPlayer",
                    "isNationalTeam": false
                }
            ],
            "sortOrder": 29323,
            "tags": [
                "MostBalancedOdds",
                "SGP",
                "MostBalancedGlobalProbability"
            ],
            "metadata": {},
            "milestoneValue": 1
        },
        {
            "id": "0QA325884847#565676860_13L84240Q11236389728Q20",
            "marketId": "325884847",
            "label": "1\u002B",
            "displayOdds": {
                "american": "\u002B152",
                "decimal": "2.52",
                "fractional": "38/25"
            },
            "trueOdds": 2.52,
            "participants": [
                {
                    "id": "31706",
                    "name": "Francisco Lindor",
                    "type": "Player",
                    "seoIdentifier": "Francisco Lindor",
                    "statistic": {
                        "prefix": "R",
                        "value": 10
                    },
                    "venueRole": "AwayPlayer",
                    "isNationalTeam": false
                }
            ],
            "sortOrder": 25260,
            "tags": [
                "MostBalancedOdds",
                "SGP",
                "MostBalancedGlobalProbability"
            ],
            "metadata": {},
            "milestoneValue": 1
        },
        {
            "id": "0QA325884847#565676895_13L84240Q1355474852Q20",
            "marketId": "325884847",
            "label": "2\u002B",
            "displayOdds": {
                "american": "\u002B940",
                "decimal": "10.40",
                "fractional": "47/5"
            },
            "trueOdds": 10.4,
            "participants": [
                {
                    "id": "31706",
                    "name": "Francisco Lindor",
                    "type": "Player",
                    "seoIdentifier": "Francisco Lindor",
                    "statistic": {
                        "prefix": "R",
                        "value": 10
                    },
                    "venueRole": "AwayPlayer",
                    "isNationalTeam": false
                }
            ],
            "sortOrder": 104095,
            "tags": [
                "SGP"
            ],
            "metadata": {},
            "milestoneValue": 2
        },
        {
            "id": "0QA325884872#565677264_13L84240Q11236389728Q20",
            "marketId": "325884872",
            "label": "1\u002B",
            "displayOdds": {
                "american": "\u2212149",
                "decimal": "1.67",
                "fractional": "100/149"
            },
            "trueOdds": 1.67114094,
            "participants": [
                {
                    "id": "32242",
                    "name": "Shohei Ohtani",
                    "type": "Player",
                    "seoIdentifier": "Shohei Ohtani",
                    "statistic": {
                        "prefix": "R",
                        "value": 10
                    },
                    "venueRole": "HomePlayer",
                    "isNationalTeam": false
                }
            ],
            "sortOrder": 16764,
            "tags": [
                "MostBalancedOdds",
                "SGP",
                "MostBalancedGlobalProbability"
            ],
            "metadata": {},
            "milestoneValue": 1
        },
        {
            "id": "0QA325884872#565677268_13L84240Q1355474852Q20",
            "marketId": "325884872",
            "label": "2\u002B",
            "displayOdds": {
                "american": "\u002B369",
                "decimal": "4.69",
                "fractional": "369/100"
            },
            "trueOdds": 4.69,
            "participants": [
                {
                    "id": "32242",
                    "name": "Shohei Ohtani",
                    "type": "Player",
                    "seoIdentifier": "Shohei Ohtani",
                    "statistic": {
                        "prefix": "R",
                        "value": 10
                    },
                    "venueRole": "HomePlayer",
                    "isNationalTeam": false
                }
            ],
            "sortOrder": 46968,
            "tags": [
                "SGP"
            ],
            "metadata": {},
            "milestoneValue": 2
        },
        {
            "id": "0QA325884886#565676691_13L84240Q11236389728Q20",
            "marketId": "325884886",
            "label": "1\u002B",
            "displayOdds": {
                "american": "\u002B220",
                "decimal": "3.20",
                "fractional": "11/5"
            },
            "trueOdds": 3.2,
            "participants": [
                {
                    "id": "806151",
                    "name": "Carson Benge",
                    "type": "Player",
                    "seoIdentifier": "Carson Benge",
                    "statistic": {
                        "prefix": "R",
                        "value": 4
                    },
                    "venueRole": "AwayPlayer",
                    "isNationalTeam": false
                }
            ],
            "sortOrder": 32091,
            "tags": [
                "MostBalancedOdds",
                "SGP",
                "MostBalancedGlobalProbability"
            ],
            "metadata": {},
            "milestoneValue": 1
        },
        {
            "id": "0QA325884976#565676976_13L84240Q11236389728Q20",
            "marketId": "325884976",
            "label": "1\u002B",
            "displayOdds": {
                "american": "\u002B196",
                "decimal": "2.96",
                "fractional": "49/25"
            },
            "trueOdds": 2.96,
            "participants": [
                {
                    "id": "32329",
                    "name": "Jorge Polanco",
                    "type": "Player",
                    "seoIdentifier": "Jorge Polanco",
                    "statistic": {
                        "prefix": "R",
                        "value": 3
                    },
                    "venueRole": "AwayPlayer",
                    "isNationalTeam": false
                }
            ],
            "sortOrder": 29676,
            "tags": [
                "MostBalancedOdds",
                "SGP",
                "MostBalancedGlobalProbability"
            ],
            "metadata": {},
            "milestoneValue": 1
        },
        {
            "id": "0QA326166724#566725406_13L84240Q11236389728Q20",
            "marketId": "326166724",
            "label": "1\u002B",
            "displayOdds": {
                "american": "\u002B214",
                "decimal": "3.14",
                "fractional": "107/50"
            },
            "trueOdds": 3.14,
            "participants": [
                {
                    "id": "112064",
                    "name": "Mark Vientos",
                    "type": "Player",
                    "seoIdentifier": "Mark Vientos",
                    "statistic": {
                        "prefix": "R",
                        "value": 5
                    },
                    "venueRole": "AwayPlayer",
                    "isNationalTeam": false
                }
            ],
            "sortOrder": 31406,
            "tags": [
                "MostBalancedOdds",
                "SGP",
                "MostBalancedGlobalProbability"
            ],
            "metadata": {},
            "milestoneValue": 1
        }
    ],
    "subscriptionPartials": {
        "markets--1290250081": {
            "entity": "markets",
            "query": "$filter=eventId eq \u002733984846\u0027 AND clientMetadata/subCategoryId eq \u002717844\u0027 AND tags/all(t: t ne \u0027SportcastBetBuilder\u0027)",
            "locale": "en"
        }
    }
}