{
  "markets": [
    {
      "id": "325619265",
      "eventId": "33972083",
      "sportId": "2",
      "leagueId": "42648",
      "name": "Brook Lopez Blocks",
      "subcategoryId": "16484",
      "componentMapping": {
        "primary": 331,
        "fallback": 0
      },
      "marketType": {
        "id": "12195",
        "betOfferTypeId": 0,
        "name": "Blocks Milestones"
      },
      "subscriptionKey": "markets-1277499878",
      "sortOrder": 1,
      "tags": [
        "SGP",
        "YourBetEligible",
        "Cashout",
        "IgnoreSortOrderOnPush",
        "PlayerProps"
      ],
      "correlatedId": "33972083|12195|2:55189",
      "dynamicMetadata": {}
    },
    {
      "id": "325618966",
      "eventId": "33972083",
      "sportId": "2",
      "leagueId": "42648",
      "name": "Kristaps Porzingis Blocks",
      "subcategoryId": "16484",
      "componentMapping": {
        "primary": 331,
        "fallback": 0
      },
      "marketType": {
        "id": "12195",
        "betOfferTypeId": 0,
        "name": "Blocks Milestones"
      },
      "subscriptionKey": "markets-1277499878",
      "sortOrder": 2,
      "tags": [
        "SGP",
        "YourBetEligible",
        "Cashout",
        "IgnoreSortOrderOnPush",
        "PlayerProps"
      ],
      "correlatedId": "33972083|12195|2:55135",
      "dynamicMetadata": {}
    },
    {
      "id": "325619500",
      "eventId": "33972083",
      "sportId": "2",
      "leagueId": "42648",
      "name": "Derrick Jones Jr. Blocks",
      "subcategoryId": "16484",
      "componentMapping": {
        "primary": 331,
        "fallback": 0
      },
      "marketType": {
        "id": "12195",
        "betOfferTypeId": 0,
        "name": "Blocks Milestones"
      },
      "subscriptionKey": "markets-1277499878",
      "sortOrder": 3,
      "tags": [
        "SGP",
        "YourBetEligible",
        "Cashout",
        "IgnoreSortOrderOnPush",
        "PlayerProps"
      ],
      "correlatedId": "33972083|12195|2:101052",
      "dynamicMetadata": {}
    },
    {
      "id": "325619352",
      "eventId": "33972083",
      "sportId": "2",
      "leagueId": "42648",
      "name": "Draymond Green Blocks",
      "subcategoryId": "16484",
      "componentMapping": {
        "primary": 331,
        "fallback": 0
      },
      "marketType": {
        "id": "12195",
        "betOfferTypeId": 0,
        "name": "Blocks Milestones"
      },
      "subscriptionKey": "markets-1277499878",
      "sortOrder": 4,
      "tags": [
        "SGP",
        "YourBetEligible",
        "Cashout",
        "IgnoreSortOrderOnPush",
        "PlayerProps"
      ],
      "correlatedId": "33972083|12195|2:55152",
      "dynamicMetadata": {}
    },
    {
      "id": "325619402",
      "eventId": "33972083",
      "sportId": "2",
      "leagueId": "42648",
      "name": "Kawhi Leonard Blocks",
      "subcategoryId": "16484",
      "componentMapping": {
        "primary": 331,
        "fallback": 0
      },
      "marketType": {
        "id": "12195",
        "betOfferTypeId": 0,
        "name": "Blocks Milestones"
      },
      "subscriptionKey": "markets-1277499878",
      "sortOrder": 5,
      "tags": [
        "SGP",
        "YourBetEligible",
        "Cashout",
        "IgnoreSortOrderOnPush",
        "PlayerProps"
      ],
      "correlatedId": "33972083|12195|2:55165",
      "dynamicMetadata": {}
    },
    {
      "id": "325619052",
      "eventId": "33972083",
      "sportId": "2",
      "leagueId": "42648",
      "name": "Stephen Curry Blocks",
      "subcategoryId": "16484",
      "componentMapping": {
        "primary": 331,
        "fallback": 0
      },
      "marketType": {
        "id": "12195",
        "betOfferTypeId": 0,
        "name": "Blocks Milestones"
      },
      "subscriptionKey": "markets-1277499878",
      "sortOrder": 6,
      "tags": [
        "SGP",
        "YourBetEligible",
        "Cashout",
        "IgnoreSortOrderOnPush",
        "PlayerProps"
      ],
      "correlatedId": "33972083|12195|2:55150",
      "dynamicMetadata": {}
    },
    {
      "id": "325619503",
      "eventId": "33972083",
      "sportId": "2",
      "leagueId": "42648",
      "name": "Gui Santos Blocks",
      "subcategoryId": "16484",
      "componentMapping": {
        "primary": 331,
        "fallback": 0
      },
      "marketType": {
        "id": "12195",
        "betOfferTypeId": 0,
        "name": "Blocks Milestones"
      },
      "subscriptionKey": "markets-1277499878",
      "sortOrder": 7,
      "tags": [
        "SGP",
        "YourBetEligible",
        "Cashout",
        "IgnoreSortOrderOnPush",
        "PlayerProps"
      ],
      "correlatedId": "33972083|12195|2:153788",
      "dynamicMetadata": {}
    },
    {
      "id": "325619061",
      "eventId": "33972083",
      "sportId": "2",
      "leagueId": "42648",
      "name": "Kris Dunn Blocks",
      "subcategoryId": "16484",
      "componentMapping": {
        "primary": 331,
        "fallback": 0
      },
      "marketType": {
        "id": "12195",
        "betOfferTypeId": 0,
        "name": "Blocks Milestones"
      },
      "subscriptionKey": "markets-1277499878",
      "sortOrder": 8,
      "tags": [
        "SGP",
        "YourBetEligible",
        "Cashout",
        "IgnoreSortOrderOnPush",
        "PlayerProps"
      ],
      "correlatedId": "33972083|12195|2:55124",
      "dynamicMetadata": {}
    },
    {
      "id": "325619242",
      "eventId": "33972083",
      "sportId": "2",
      "leagueId": "42648",
      "name": "Brandin Podziemski Blocks",
      "subcategoryId": "16484",
      "componentMapping": {
        "primary": 331,
        "fallback": 0
      },
      "marketType": {
        "id": "12195",
        "betOfferTypeId": 0,
        "name": "Blocks Milestones"
      },
      "subscriptionKey": "markets-1277499878",
      "sortOrder": 9,
      "tags": [
        "SGP",
        "YourBetEligible",
        "Cashout",
        "IgnoreSortOrderOnPush",
        "PlayerProps"
      ],
      "correlatedId": "33972083|12195|2:128709",
      "dynamicMetadata": {}
    },
    {
      "id": "325619009",
      "eventId": "33972083",
      "sportId": "2",
      "leagueId": "42648",
      "name": "Darius Garland Blocks",
      "subcategoryId": "16484",
      "componentMapping": {
        "primary": 331,
        "fallback": 0
      },
      "marketType": {
        "id": "12195",
        "betOfferTypeId": 0,
        "name": "Blocks Milestones"
      },
      "subscriptionKey": "markets-1277499878",
      "sortOrder": 10,
      "tags": [
        "SGP",
        "YourBetEligible",
        "Cashout",
        "IgnoreSortOrderOnPush",
        "PlayerProps"
      ],
      "correlatedId": "33972083|12195|2:55785",
      "dynamicMetadata": {}
    }
  ],
  "selections": [
    {
      "id": "0QA325618966#564382445_13L42648Q11130272651Q20",
      "marketId": "325618966",
      "label": "1\u002B",
      "displayOdds": {
        "american": "\u2212269",
        "decimal": "1.37",
        "fractional": "100/269"
      },
      "trueOdds": 1.37174722,
      "participants": [
        {
          "id": "32998",
          "name": "Kristaps Porzingis",
          "type": "Player",
          "seoIdentifier": "Kristaps Porzingis",
          "statistic": {
            "prefix": "BLKPG",
            "value": 1.2
          },
          "venueRole": "AwayPlayer",
          "isNationalTeam": false
        }
      ],
      "sortOrder": 13745,
      "tags": [
        "SGP"
      ],
      "metadata": {},
      "milestoneValue": 1
    },
    {
      "id": "0QA325618966#564382455_13L42648Q1160400555Q20",
      "marketId": "325618966",
      "label": "2\u002B",
      "displayOdds": {
        "american": "\u002B170",
        "decimal": "2.70",
        "fractional": "17/10"
      },
      "trueOdds": 2.7,
      "participants": [
        {
          "id": "32998",
          "name": "Kristaps Porzingis",
          "type": "Player",
          "seoIdentifier": "Kristaps Porzingis",
          "statistic": {
            "prefix": "BLKPG",
            "value": 1.2
          },
          "venueRole": "AwayPlayer",
          "isNationalTeam": false
        }
      ],
      "sortOrder": 27055,
      "tags": [
        "MostBalancedOdds",
        "SGP",
        "MostBalancedGlobalProbability"
      ],
      "metadata": {},
      "milestoneValue": 2
    },
    {
      "id": "0QA325618966#564382511_13L42648Q1663323674Q20",
      "marketId": "325618966",
      "label": "3\u002B",
      "displayOdds": {
        "american": "\u002B568",
        "decimal": "6.68",
        "fractional": "142/25"
      },
      "trueOdds": 6.68,
      "participants": [
        {
          "id": "32998",
          "name": "Kristaps Porzingis",
          "type": "Player",
          "seoIdentifier": "Kristaps Porzingis",
          "statistic": {
            "prefix": "BLKPG",
            "value": 1.2
          },
          "venueRole": "AwayPlayer",
          "isNationalTeam": false
        }
      ],
      "sortOrder": 66811,
      "tags": [
        "SGP"
      ],
      "metadata": {},
      "milestoneValue": 3
    },
    {
      "id": "0QA325619009#564382684_13L42648Q11130272651Q20",
      "marketId": "325619009",
      "label": "1\u002B",
      "displayOdds": {
        "american": "\u002B298",
        "decimal": "3.98",
        "fractional": "149/50"
      },
      "trueOdds": 3.98,
      "participants": [
        {
          "id": "32989",
          "name": "Darius Garland",
          "type": "Player",
          "seoIdentifier": "Darius Garland",
          "statistic": {
            "prefix": "BLKPG",
            "value": 0.2
          },
          "venueRole": "HomePlayer",
          "isNationalTeam": false
        }
      ],
      "sortOrder": 39884,
      "tags": [
        "MostBalancedOdds",
        "SGP",
        "MostBalancedGlobalProbability"
      ],
      "metadata": {},
      "milestoneValue": 1
    },
    {
      "id": "0QA325619052#564382261_13L42648Q11130272651Q20",
      "marketId": "325619052",
      "label": "1\u002B",
      "displayOdds": {
        "american": "\u002B175",
        "decimal": "2.75",
        "fractional": "7/4"
      },
      "trueOdds": 2.75,
      "participants": [
        {
          "id": "33049",
          "name": "Stephen Curry",
          "type": "Player",
          "seoIdentifier": "Stephen Curry",
          "statistic": {
            "prefix": "BLKPG",
            "value": 0.4
          },
          "venueRole": "AwayPlayer",
          "isNationalTeam": false
        }
      ],
      "sortOrder": 27561,
      "tags": [
        "MostBalancedOdds",
        "SGP",
        "MostBalancedGlobalProbability"
      ],
      "metadata": {},
      "milestoneValue": 1
    },
    {
      "id": "0QA325619052#564382282_13L42648Q1160400555Q20",
      "marketId": "325619052",
      "label": "2\u002B",
      "displayOdds": {
        "american": "\u002B980",
        "decimal": "10.80",
        "fractional": "49/5"
      },
      "trueOdds": 10.8,
      "participants": [
        {
          "id": "33049",
          "name": "Stephen Curry",
          "type": "Player",
          "seoIdentifier": "Stephen Curry",
          "statistic": {
            "prefix": "BLKPG",
            "value": 0.4
          },
          "venueRole": "AwayPlayer",
          "isNationalTeam": false
        }
      ],
      "sortOrder": 108082,
      "tags": [
        "SGP"
      ],
      "metadata": {},
      "milestoneValue": 2
    },
    {
      "id": "0QA325619061#564382366_13L42648Q11130272651Q20",
      "marketId": "325619061",
      "label": "1\u002B",
      "displayOdds": {
        "american": "\u002B265",
        "decimal": "3.65",
        "fractional": "53/20"
      },
      "trueOdds": 3.65,
      "participants": [
        {
          "id": "32966",
          "name": "Kris Dunn",
          "type": "Player",
          "seoIdentifier": "Kris Dunn",
          "statistic": {
            "prefix": "BLKPG",
            "value": 0.2
          },
          "venueRole": "HomePlayer",
          "isNationalTeam": false
        }
      ],
      "sortOrder": 36566,
      "tags": [
        "MostBalancedOdds",
        "SGP",
        "MostBalancedGlobalProbability"
      ],
      "metadata": {},
      "milestoneValue": 1
    },
    {
      "id": "0QA325619242#564383106_13L42648Q11130272651Q20",
      "marketId": "325619242",
      "label": "1\u002B",
      "displayOdds": {
        "american": "\u002B287",
        "decimal": "3.87",
        "fractional": "287/100"
      },
      "trueOdds": 3.87,
      "participants": [
        {
          "id": "713772",
          "name": "Brandin Podziemski",
          "type": "Player",
          "seoIdentifier": "Brandin Podziemski",
          "statistic": {
            "prefix": "BLKPG",
            "value": 0.2
          },
          "venueRole": "AwayPlayer",
          "isNationalTeam": false
        }
      ],
      "sortOrder": 38706,
      "tags": [
        "MostBalancedOdds",
        "SGP",
        "MostBalancedGlobalProbability"
      ],
      "metadata": {},
      "milestoneValue": 1
    },
    {
      "id": "0QA325619265#564383117_13L42648Q11130272651Q20",
      "marketId": "325619265",
      "label": "1\u002B",
      "displayOdds": {
        "american": "\u2212319",
        "decimal": "1.31",
        "fractional": "100/319"
      },
      "trueOdds": 1.31347963,
      "participants": [
        {
          "id": "33171",
          "name": "Brook Lopez",
          "type": "Player",
          "seoIdentifier": "Brook Lopez",
          "statistic": {
            "prefix": "BLKPG",
            "value": 1.2
          },
          "venueRole": "HomePlayer",
          "isNationalTeam": false
        }
      ],
      "sortOrder": 13117,
      "tags": [
        "SGP"
      ],
      "metadata": {},
      "milestoneValue": 1
    },
    {
      "id": "0QA325619265#564383179_13L42648Q1160400555Q20",
      "marketId": "325619265",
      "label": "2\u002B",
      "displayOdds": {
        "american": "\u002B144",
        "decimal": "2.44",
        "fractional": "36/25"
      },
      "trueOdds": 2.44,
      "participants": [
        {
          "id": "33171",
          "name": "Brook Lopez",
          "type": "Player",
          "seoIdentifier": "Brook Lopez",
          "statistic": {
            "prefix": "BLKPG",
            "value": 1.2
          },
          "venueRole": "HomePlayer",
          "isNationalTeam": false
        }
      ],
      "sortOrder": 24479,
      "tags": [
        "MostBalancedOdds",
        "SGP",
        "MostBalancedGlobalProbability"
      ],
      "metadata": {},
      "milestoneValue": 2
    },
    {
      "id": "0QA325619265#564383192_13L42648Q1663323674Q20",
      "marketId": "325619265",
      "label": "3\u002B",
      "displayOdds": {
        "american": "\u002B460",
        "decimal": "5.60",
        "fractional": "23/5"
      },
      "trueOdds": 5.6,
      "participants": [
        {
          "id": "33171",
          "name": "Brook Lopez",
          "type": "Player",
          "seoIdentifier": "Brook Lopez",
          "statistic": {
            "prefix": "BLKPG",
            "value": 1.2
          },
          "venueRole": "HomePlayer",
          "isNationalTeam": false
        }
      ],
      "sortOrder": 56092,
      "tags": [
        "SGP"
      ],
      "metadata": {},
      "milestoneValue": 3
    },
    {
      "id": "0QA325619352#564383126_13L42648Q11130272651Q20",
      "marketId": "325619352",
      "label": "1\u002B",
      "displayOdds": {
        "american": "\u2212138",
        "decimal": "1.72",
        "fractional": "50/69"
      },
      "trueOdds": 1.72463769,
      "participants": [
        {
          "id": "33052",
          "name": "Draymond Green",
          "type": "Player",
          "seoIdentifier": "Draymond Green",
          "statistic": {
            "prefix": "BLKPG",
            "value": 0.6
          },
          "venueRole": "AwayPlayer",
          "isNationalTeam": false
        }
      ],
      "sortOrder": 17226,
      "tags": [
        "MostBalancedOdds",
        "SGP",
        "MostBalancedGlobalProbability"
      ],
      "metadata": {},
      "milestoneValue": 1
    },
    {
      "id": "0QA325619352#564383289_13L42648Q1160400555Q20",
      "marketId": "325619352",
      "label": "2\u002B",
      "displayOdds": {
        "american": "\u002B341",
        "decimal": "4.41",
        "fractional": "341/100"
      },
      "trueOdds": 4.41,
      "participants": [
        {
          "id": "33052",
          "name": "Draymond Green",
          "type": "Player",
          "seoIdentifier": "Draymond Green",
          "statistic": {
            "prefix": "BLKPG",
            "value": 0.6
          },
          "venueRole": "AwayPlayer",
          "isNationalTeam": false
        }
      ],
      "sortOrder": 44189,
      "tags": [
        "SGP"
      ],
      "metadata": {},
      "milestoneValue": 2
    },
    {
      "id": "0QA325619352#565106211_13L42648Q1663323674Q20",
      "marketId": "325619352",
      "label": "3\u002B",
      "displayOdds": {
        "american": "\u002B1160",
        "decimal": "12.60",
        "fractional": "58/5"
      },
      "trueOdds": 12.6,
      "participants": [
        {
          "id": "33052",
          "name": "Draymond Green",
          "type": "Player",
          "seoIdentifier": "Draymond Green",
          "statistic": {
            "prefix": "BLKPG",
            "value": 0.6
          },
          "venueRole": "AwayPlayer",
          "isNationalTeam": false
        }
      ],
      "sortOrder": 126011,
      "tags": [
        "SGP"
      ],
      "metadata": {},
      "milestoneValue": 3
    },
    {
      "id": "0QA325619402#564384521_13L42648Q11130272651Q20",
      "marketId": "325619402",
      "label": "1\u002B",
      "displayOdds": {
        "american": "\u002B144",
        "decimal": "2.44",
        "fractional": "36/25"
      },
      "trueOdds": 2.44,
      "participants": [
        {
          "id": "33102",
          "name": "Kawhi Leonard",
          "type": "Player",
          "seoIdentifier": "Kawhi Leonard",
          "statistic": {
            "prefix": "BLKPG",
            "value": 0.4
          },
          "venueRole": "HomePlayer",
          "isNationalTeam": false
        }
      ],
      "sortOrder": 24421,
      "tags": [
        "MostBalancedOdds",
        "SGP",
        "MostBalancedGlobalProbability"
      ],
      "metadata": {},
      "milestoneValue": 1
    },
    {
      "id": "0QA325619402#564384551_13L42648Q1160400555Q20",
      "marketId": "325619402",
      "label": "2\u002B",
      "displayOdds": {
        "american": "\u002B790",
        "decimal": "8.90",
        "fractional": "79/10"
      },
      "trueOdds": 8.9,
      "participants": [
        {
          "id": "33102",
          "name": "Kawhi Leonard",
          "type": "Player",
          "seoIdentifier": "Kawhi Leonard",
          "statistic": {
            "prefix": "BLKPG",
            "value": 0.4
          },
          "venueRole": "HomePlayer",
          "isNationalTeam": false
        }
      ],
      "sortOrder": 89051,
      "tags": [
        "SGP"
      ],
      "metadata": {},
      "milestoneValue": 2
    },
    {
      "id": "0QA325619500#564383104_13L42648Q11130272651Q20",
      "marketId": "325619500",
      "label": "1\u002B",
      "displayOdds": {
        "american": "\u2212191",
        "decimal": "1.52",
        "fractional": "100/191"
      },
      "trueOdds": 1.52356021,
      "participants": [
        {
          "id": "33160",
          "name": "Derrick Jones Jr.",
          "type": "Player",
          "seoIdentifier": "Derrick Jones Jr.",
          "statistic": {
            "prefix": "BLKPG",
            "value": 1
          },
          "venueRole": "HomePlayer",
          "isNationalTeam": false
        }
      ],
      "sortOrder": 15204,
      "tags": [
        "MostBalancedOdds",
        "SGP",
        "MostBalancedGlobalProbability"
      ],
      "metadata": {},
      "milestoneValue": 1
    },
    {
      "id": "0QA325619500#564383271_13L42648Q1160400555Q20",
      "marketId": "325619500",
      "label": "2\u002B",
      "displayOdds": {
        "american": "\u002B243",
        "decimal": "3.43",
        "fractional": "243/100"
      },
      "trueOdds": 3.43,
      "participants": [
        {
          "id": "33160",
          "name": "Derrick Jones Jr.",
          "type": "Player",
          "seoIdentifier": "Derrick Jones Jr.",
          "statistic": {
            "prefix": "BLKPG",
            "value": 1
          },
          "venueRole": "HomePlayer",
          "isNationalTeam": false
        }
      ],
      "sortOrder": 34371,
      "tags": [
        "SGP"
      ],
      "metadata": {},
      "milestoneValue": 2
    },
    {
      "id": "0QA325619500#564383389_13L42648Q1663323674Q20",
      "marketId": "325619500",
      "label": "3\u002B",
      "displayOdds": {
        "american": "\u002B810",
        "decimal": "9.10",
        "fractional": "81/10"
      },
      "trueOdds": 9.1,
      "participants": [
        {
          "id": "33160",
          "name": "Derrick Jones Jr.",
          "type": "Player",
          "seoIdentifier": "Derrick Jones Jr.",
          "statistic": {
            "prefix": "BLKPG",
            "value": 1
          },
          "venueRole": "HomePlayer",
          "isNationalTeam": false
        }
      ],
      "sortOrder": 91089,
      "tags": [
        "SGP"
      ],
      "metadata": {},
      "milestoneValue": 3
    },
    {
      "id": "0QA325619503#564384357_13L42648Q11130272651Q20",
      "marketId": "325619503",
      "label": "1\u002B",
      "displayOdds": {
        "american": "\u002B193",
        "decimal": "2.93",
        "fractional": "193/100"
      },
      "trueOdds": 2.93,
      "participants": [
        {
          "id": "649707",
          "name": "Gui Santos",
          "type": "Player",
          "seoIdentifier": "Gui Santos",
          "statistic": {
            "prefix": "BLKPG",
            "value": 0.3
          },
          "venueRole": "AwayPlayer",
          "isNationalTeam": false
        }
      ],
      "sortOrder": 29357,
      "tags": [
        "MostBalancedOdds",
        "SGP",
        "MostBalancedGlobalProbability"
      ],
      "metadata": {},
      "milestoneValue": 1
    },
    {
      "id": "0QA325619503#564384402_13L42648Q1160400555Q20",
      "marketId": "325619503",
      "label": "2\u002B",
      "displayOdds": {
        "american": "\u002B1060",
        "decimal": "11.60",
        "fractional": "53/5"
      },
      "trueOdds": 11.6,
      "participants": [
        {
          "id": "649707",
          "name": "Gui Santos",
          "type": "Player",
          "seoIdentifier": "Gui Santos",
          "statistic": {
            "prefix": "BLKPG",
            "value": 0.3
          },
          "venueRole": "AwayPlayer",
          "isNationalTeam": false
        }
      ],
      "sortOrder": 116002,
      "tags": [
        "SGP"
      ],
      "metadata": {},
      "milestoneValue": 2
    }
  ],
  "subscriptionPartials": {
    "markets-1277499878": {
      "entity": "markets",
      "query": "$filter=eventId eq \u002733972083\u0027 AND clientMetadata/subCategoryId eq \u002716484\u0027 AND tags/all(t: t ne \u0027SportcastBetBuilder\u0027)",
      "locale": "en"
    }
  }
}