{
  "markets": [
    {
      "id": "320168067",
      "eventId": "33858679",
      "sportId": "2",
      "leagueId": "42648",
      "name": "Donovan Mitchell Steals",
      "subcategoryId": "16485",
      "componentMapping": {
        "primary": 331,
        "fallback": 0
      },
      "marketType": {
        "id": "12196",
        "betOfferTypeId": 0,
        "name": "Steals Milestones"
      },
      "subscriptionKey": "markets-230772663",
      "sortOrder": 1,
      "tags": [
        "SGP",
        "YourBetEligible",
        "Cashout",
        "IgnoreSortOrderOnPush",
        "PlayerProps"
      ],
      "correlatedId": "33858679|12196|2:55246",
      "dynamicMetadata": {}
    },
    {
      "id": "320168294",
      "eventId": "33858679",
      "sportId": "2",
      "leagueId": "42648",
      "name": "Keon Ellis Steals",
      "subcategoryId": "16485",
      "componentMapping": {
        "primary": 331,
        "fallback": 0
      },
      "marketType": {
        "id": "12196",
        "betOfferTypeId": 0,
        "name": "Steals Milestones"
      },
      "subscriptionKey": "markets-230772663",
      "sortOrder": 2,
      "tags": [
        "SGP",
        "YourBetEligible",
        "Cashout",
        "IgnoreSortOrderOnPush",
        "PlayerProps"
      ],
      "correlatedId": "33858679|12196|2:131607",
      "dynamicMetadata": {}
    },
    {
      "id": "320168014",
      "eventId": "33858679",
      "sportId": "2",
      "leagueId": "42648",
      "name": "Desmond Bane Steals",
      "subcategoryId": "16485",
      "componentMapping": {
        "primary": 331,
        "fallback": 0
      },
      "marketType": {
        "id": "12196",
        "betOfferTypeId": 0,
        "name": "Steals Milestones"
      },
      "subscriptionKey": "markets-230772663",
      "sortOrder": 3,
      "tags": [
        "SGP",
        "YourBetEligible",
        "Cashout",
        "IgnoreSortOrderOnPush",
        "PlayerProps"
      ],
      "correlatedId": "33858679|12196|2:117287",
      "dynamicMetadata": {}
    },
    {
      "id": "320168187",
      "eventId": "33858679",
      "sportId": "2",
      "leagueId": "42648",
      "name": "James Harden Steals",
      "subcategoryId": "16485",
      "componentMapping": {
        "primary": 331,
        "fallback": 0
      },
      "marketType": {
        "id": "12196",
        "betOfferTypeId": 0,
        "name": "Steals Milestones"
      },
      "subscriptionKey": "markets-230772663",
      "sortOrder": 4,
      "tags": [
        "SGP",
        "YourBetEligible",
        "Cashout",
        "IgnoreSortOrderOnPush",
        "PlayerProps"
      ],
      "correlatedId": "33858679|12196|2:55155",
      "dynamicMetadata": {}
    },
    {
      "id": "320168564",
      "eventId": "33858679",
      "sportId": "2",
      "leagueId": "42648",
      "name": "Tristan da Silva Steals",
      "subcategoryId": "16485",
      "componentMapping": {
        "primary": 331,
        "fallback": 0
      },
      "marketType": {
        "id": "12196",
        "betOfferTypeId": 0,
        "name": "Steals Milestones"
      },
      "subscriptionKey": "markets-230772663",
      "sortOrder": 5,
      "tags": [
        "SGP",
        "YourBetEligible",
        "Cashout",
        "IgnoreSortOrderOnPush",
        "PlayerProps"
      ],
      "correlatedId": "33858679|12196|2:132039",
      "dynamicMetadata": {}
    },
    {
      "id": "320168460",
      "eventId": "33858679",
      "sportId": "2",
      "leagueId": "42648",
      "name": "Jevon Carter Steals",
      "subcategoryId": "16485",
      "componentMapping": {
        "primary": 331,
        "fallback": 0
      },
      "marketType": {
        "id": "12196",
        "betOfferTypeId": 0,
        "name": "Steals Milestones"
      },
      "subscriptionKey": "markets-230772663",
      "sortOrder": 6,
      "tags": [
        "SGP",
        "YourBetEligible",
        "Cashout",
        "IgnoreSortOrderOnPush",
        "PlayerProps"
      ],
      "correlatedId": "33858679|12196|2:101816",
      "dynamicMetadata": {}
    },
    {
      "id": "320168395",
      "eventId": "33858679",
      "sportId": "2",
      "leagueId": "42648",
      "name": "Dean Wade Steals",
      "subcategoryId": "16485",
      "componentMapping": {
        "primary": 331,
        "fallback": 0
      },
      "marketType": {
        "id": "12196",
        "betOfferTypeId": 0,
        "name": "Steals Milestones"
      },
      "subscriptionKey": "markets-230772663",
      "sortOrder": 7,
      "tags": [
        "SGP",
        "YourBetEligible",
        "Cashout",
        "IgnoreSortOrderOnPush",
        "PlayerProps"
      ],
      "correlatedId": "33858679|12196|2:62528",
      "dynamicMetadata": {}
    },
    {
      "id": "320168065",
      "eventId": "33858679",
      "sportId": "2",
      "leagueId": "42648",
      "name": "Sam Merrill Steals",
      "subcategoryId": "16485",
      "componentMapping": {
        "primary": 331,
        "fallback": 0
      },
      "marketType": {
        "id": "12196",
        "betOfferTypeId": 0,
        "name": "Steals Milestones"
      },
      "subscriptionKey": "markets-230772663",
      "sortOrder": 8,
      "tags": [
        "SGP",
        "YourBetEligible",
        "Cashout",
        "IgnoreSortOrderOnPush",
        "PlayerProps"
      ],
      "correlatedId": "33858679|12196|2:118643",
      "dynamicMetadata": {}
    },
    {
      "id": "320168507",
      "eventId": "33858679",
      "sportId": "2",
      "leagueId": "42648",
      "name": "Paolo Banchero Steals",
      "subcategoryId": "16485",
      "componentMapping": {
        "primary": 331,
        "fallback": 0
      },
      "marketType": {
        "id": "12196",
        "betOfferTypeId": 0,
        "name": "Steals Milestones"
      },
      "subscriptionKey": "markets-230772663",
      "sortOrder": 9,
      "tags": [
        "SGP",
        "YourBetEligible",
        "Cashout",
        "IgnoreSortOrderOnPush",
        "PlayerProps"
      ],
      "correlatedId": "33858679|12196|2:153762",
      "dynamicMetadata": {}
    },
    {
      "id": "320168287",
      "eventId": "33858679",
      "sportId": "2",
      "leagueId": "42648",
      "name": "Wendell Carter Jr. Steals",
      "subcategoryId": "16485",
      "componentMapping": {
        "primary": 331,
        "fallback": 0
      },
      "marketType": {
        "id": "12196",
        "betOfferTypeId": 0,
        "name": "Steals Milestones"
      },
      "subscriptionKey": "markets-230772663",
      "sortOrder": 10,
      "tags": [
        "SGP",
        "YourBetEligible",
        "Cashout",
        "IgnoreSortOrderOnPush",
        "PlayerProps"
      ],
      "correlatedId": "33858679|12196|2:55782",
      "dynamicMetadata": {}
    },
    {
      "id": "320168392",
      "eventId": "33858679",
      "sportId": "2",
      "leagueId": "42648",
      "name": "Evan Mobley Steals",
      "subcategoryId": "16485",
      "componentMapping": {
        "primary": 331,
        "fallback": 0
      },
      "marketType": {
        "id": "12196",
        "betOfferTypeId": 0,
        "name": "Steals Milestones"
      },
      "subscriptionKey": "markets-230772663",
      "sortOrder": 11,
      "tags": [
        "SGP",
        "YourBetEligible",
        "Cashout",
        "IgnoreSortOrderOnPush",
        "PlayerProps"
      ],
      "correlatedId": "33858679|12196|2:127013",
      "dynamicMetadata": {}
    }
  ],
  "selections": [
    {
      "id": "0QA320168014#541398533_13L42648Q1-906224463Q20",
      "marketId": "320168014",
      "label": "1\u002B",
      "displayOdds": {
        "american": "\u2212255",
        "decimal": "1.39",
        "fractional": "20/51"
      },
      "trueOdds": 1.39215687,
      "participants": [
        {
          "id": "527237",
          "name": "Desmond Bane",
          "type": "Player",
          "seoIdentifier": "Desmond Bane",
          "statistic": {
            "prefix": "STLPG",
            "value": 1
          },
          "venueRole": "AwayPlayer",
          "isNationalTeam": false
        }
      ],
      "sortOrder": 13932,
      "tags": [
        "SGP"
      ],
      "metadata": {},
      "milestoneValue": 1
    },
    {
      "id": "0QA320168014#541398648_13L42648Q12102868148Q20",
      "marketId": "320168014",
      "label": "2\u002B",
      "displayOdds": {
        "american": "\u002B180",
        "decimal": "2.80",
        "fractional": "9/5"
      },
      "trueOdds": 2.8,
      "participants": [
        {
          "id": "527237",
          "name": "Desmond Bane",
          "type": "Player",
          "seoIdentifier": "Desmond Bane",
          "statistic": {
            "prefix": "STLPG",
            "value": 1
          },
          "venueRole": "AwayPlayer",
          "isNationalTeam": false
        }
      ],
      "sortOrder": 28048,
      "tags": [
        "MostBalancedOdds",
        "SGP",
        "MostBalancedGlobalProbability"
      ],
      "metadata": {},
      "milestoneValue": 2
    },
    {
      "id": "0QA320168014#541398746_13L42648Q1847184703Q20",
      "marketId": "320168014",
      "label": "3\u002B",
      "displayOdds": {
        "american": "\u002B590",
        "decimal": "6.90",
        "fractional": "59/10"
      },
      "trueOdds": 6.9,
      "participants": [
        {
          "id": "527237",
          "name": "Desmond Bane",
          "type": "Player",
          "seoIdentifier": "Desmond Bane",
          "statistic": {
            "prefix": "STLPG",
            "value": 1
          },
          "venueRole": "AwayPlayer",
          "isNationalTeam": false
        }
      ],
      "sortOrder": 69046,
      "tags": [
        "SGP"
      ],
      "metadata": {},
      "milestoneValue": 3
    },
    {
      "id": "0QA320168065#541398599_13L42648Q1-906224463Q20",
      "marketId": "320168065",
      "label": "1\u002B",
      "displayOdds": {
        "american": "\u2212171",
        "decimal": "1.58",
        "fractional": "100/171"
      },
      "trueOdds": 1.58479533,
      "participants": [
        {
          "id": "527270",
          "name": "Sam Merrill",
          "type": "Player",
          "seoIdentifier": "Sam Merrill",
          "statistic": {
            "prefix": "STLPG",
            "value": 0.6
          },
          "venueRole": "HomePlayer",
          "isNationalTeam": false
        }
      ],
      "sortOrder": 15899,
      "tags": [
        "MostBalancedOdds",
        "SGP",
        "MostBalancedGlobalProbability"
      ],
      "metadata": {},
      "milestoneValue": 1
    },
    {
      "id": "0QA320168065#541398623_13L42648Q12102868148Q20",
      "marketId": "320168065",
      "label": "2\u002B",
      "displayOdds": {
        "american": "\u002B281",
        "decimal": "3.81",
        "fractional": "281/100"
      },
      "trueOdds": 3.81,
      "participants": [
        {
          "id": "527270",
          "name": "Sam Merrill",
          "type": "Player",
          "seoIdentifier": "Sam Merrill",
          "statistic": {
            "prefix": "STLPG",
            "value": 0.6
          },
          "venueRole": "HomePlayer",
          "isNationalTeam": false
        }
      ],
      "sortOrder": 38123,
      "tags": [
        "SGP"
      ],
      "metadata": {},
      "milestoneValue": 2
    },
    {
      "id": "0QA320168065#541398722_13L42648Q1847184703Q20",
      "marketId": "320168065",
      "label": "3\u002B",
      "displayOdds": {
        "american": "\u002B950",
        "decimal": "10.50",
        "fractional": "19/2"
      },
      "trueOdds": 10.5,
      "participants": [
        {
          "id": "527270",
          "name": "Sam Merrill",
          "type": "Player",
          "seoIdentifier": "Sam Merrill",
          "statistic": {
            "prefix": "STLPG",
            "value": 0.6
          },
          "venueRole": "HomePlayer",
          "isNationalTeam": false
        }
      ],
      "sortOrder": 105022,
      "tags": [
        "SGP"
      ],
      "metadata": {},
      "milestoneValue": 3
    },
    {
      "id": "0QA320168067#541397906_13L42648Q1-906224463Q20",
      "marketId": "320168067",
      "label": "1\u002B",
      "displayOdds": {
        "american": "\u2212504",
        "decimal": "1.19",
        "fractional": "25/126"
      },
      "trueOdds": 1.1984127,
      "participants": [
        {
          "id": "33398",
          "name": "Donovan Mitchell",
          "type": "Player",
          "seoIdentifier": "Donovan Mitchell",
          "statistic": {
            "prefix": "STLPG",
            "value": 1.5
          },
          "venueRole": "HomePlayer",
          "isNationalTeam": false
        }
      ],
      "sortOrder": 11906,
      "tags": [
        "SGP"
      ],
      "metadata": {},
      "milestoneValue": 1
    },
    {
      "id": "0QA320168067#541397924_13L42648Q12102868148Q20",
      "marketId": "320168067",
      "label": "2\u002B",
      "displayOdds": {
        "american": "\u2212111",
        "decimal": "1.90",
        "fractional": "100/111"
      },
      "trueOdds": 1.90090091,
      "participants": [
        {
          "id": "33398",
          "name": "Donovan Mitchell",
          "type": "Player",
          "seoIdentifier": "Donovan Mitchell",
          "statistic": {
            "prefix": "STLPG",
            "value": 1.5
          },
          "venueRole": "HomePlayer",
          "isNationalTeam": false
        }
      ],
      "sortOrder": 19024,
      "tags": [
        "MostBalancedOdds",
        "SGP",
        "MostBalancedGlobalProbability"
      ],
      "metadata": {},
      "milestoneValue": 2
    },
    {
      "id": "0QA320168067#541397943_13L42648Q1847184703Q20",
      "marketId": "320168067",
      "label": "3\u002B",
      "displayOdds": {
        "american": "\u002B276",
        "decimal": "3.76",
        "fractional": "69/25"
      },
      "trueOdds": 3.76,
      "participants": [
        {
          "id": "33398",
          "name": "Donovan Mitchell",
          "type": "Player",
          "seoIdentifier": "Donovan Mitchell",
          "statistic": {
            "prefix": "STLPG",
            "value": 1.5
          },
          "venueRole": "HomePlayer",
          "isNationalTeam": false
        }
      ],
      "sortOrder": 37643,
      "tags": [
        "SGP"
      ],
      "metadata": {},
      "milestoneValue": 3
    },
    {
      "id": "0QA320168067#541397964_13L42648Q11215924365Q20",
      "marketId": "320168067",
      "label": "4\u002B",
      "displayOdds": {
        "american": "\u002B760",
        "decimal": "8.60",
        "fractional": "38/5"
      },
      "trueOdds": 8.6,
      "participants": [
        {
          "id": "33398",
          "name": "Donovan Mitchell",
          "type": "Player",
          "seoIdentifier": "Donovan Mitchell",
          "statistic": {
            "prefix": "STLPG",
            "value": 1.5
          },
          "venueRole": "HomePlayer",
          "isNationalTeam": false
        }
      ],
      "sortOrder": 86064,
      "tags": [
        "SGP"
      ],
      "metadata": {},
      "milestoneValue": 4
    },
    {
      "id": "0QA320168187#541398928_13L42648Q1-906224463Q20",
      "marketId": "320168187",
      "label": "1\u002B",
      "displayOdds": {
        "american": "\u2212245",
        "decimal": "1.40",
        "fractional": "20/49"
      },
      "trueOdds": 1.40816327,
      "participants": [
        {
          "id": "33070",
          "name": "James Harden",
          "type": "Player",
          "seoIdentifier": "James Harden",
          "statistic": {
            "prefix": "STLPG",
            "value": 1.1
          },
          "venueRole": "HomePlayer",
          "isNationalTeam": false
        }
      ],
      "sortOrder": 14028,
      "tags": [
        "SGP",
        "MostBalancedGlobalProbability"
      ],
      "metadata": {},
      "milestoneValue": 1
    },
    {
      "id": "0QA320168187#541399040_13L42648Q12102868148Q20",
      "marketId": "320168187",
      "label": "2\u002B",
      "displayOdds": {
        "american": "\u002B187",
        "decimal": "2.87",
        "fractional": "187/100"
      },
      "trueOdds": 2.87,
      "participants": [
        {
          "id": "33070",
          "name": "James Harden",
          "type": "Player",
          "seoIdentifier": "James Harden",
          "statistic": {
            "prefix": "STLPG",
            "value": 1.1
          },
          "venueRole": "HomePlayer",
          "isNationalTeam": false
        }
      ],
      "sortOrder": 28740,
      "tags": [
        "MostBalancedOdds",
        "SGP"
      ],
      "metadata": {},
      "milestoneValue": 2
    },
    {
      "id": "0QA320168187#541399121_13L42648Q1847184703Q20",
      "marketId": "320168187",
      "label": "3\u002B",
      "displayOdds": {
        "american": "\u002B620",
        "decimal": "7.20",
        "fractional": "31/5"
      },
      "trueOdds": 7.2,
      "participants": [
        {
          "id": "33070",
          "name": "James Harden",
          "type": "Player",
          "seoIdentifier": "James Harden",
          "statistic": {
            "prefix": "STLPG",
            "value": 1.1
          },
          "venueRole": "HomePlayer",
          "isNationalTeam": false
        }
      ],
      "sortOrder": 72021,
      "tags": [
        "SGP"
      ],
      "metadata": {},
      "milestoneValue": 3
    },
    {
      "id": "0QA320168287#541399300_13L42648Q1-906224463Q20",
      "marketId": "320168287",
      "label": "1\u002B",
      "displayOdds": {
        "american": "\u2212155",
        "decimal": "1.64",
        "fractional": "20/31"
      },
      "trueOdds": 1.6451613,
      "participants": [
        {
          "id": "32972",
          "name": "Wendell Carter Jr.",
          "type": "Player",
          "seoIdentifier": "Wendell Carter Jr.",
          "statistic": {
            "prefix": "STLPG",
            "value": 0.8
          },
          "venueRole": "AwayPlayer",
          "isNationalTeam": false
        }
      ],
      "sortOrder": 16400,
      "tags": [
        "MostBalancedOdds",
        "SGP",
        "MostBalancedGlobalProbability"
      ],
      "metadata": {},
      "milestoneValue": 1
    },
    {
      "id": "0QA320168287#541399367_13L42648Q12102868148Q20",
      "marketId": "320168287",
      "label": "2\u002B",
      "displayOdds": {
        "american": "\u002B310",
        "decimal": "4.10",
        "fractional": "31/10"
      },
      "trueOdds": 4.1,
      "participants": [
        {
          "id": "32972",
          "name": "Wendell Carter Jr.",
          "type": "Player",
          "seoIdentifier": "Wendell Carter Jr.",
          "statistic": {
            "prefix": "STLPG",
            "value": 0.8
          },
          "venueRole": "AwayPlayer",
          "isNationalTeam": false
        }
      ],
      "sortOrder": 41067,
      "tags": [
        "SGP"
      ],
      "metadata": {},
      "milestoneValue": 2
    },
    {
      "id": "0QA320168287#541399435_13L42648Q1847184703Q20",
      "marketId": "320168287",
      "label": "3\u002B",
      "displayOdds": {
        "american": "\u002B1100",
        "decimal": "12.00",
        "fractional": "11/1"
      },
      "trueOdds": 12,
      "participants": [
        {
          "id": "32972",
          "name": "Wendell Carter Jr.",
          "type": "Player",
          "seoIdentifier": "Wendell Carter Jr.",
          "statistic": {
            "prefix": "STLPG",
            "value": 0.8
          },
          "venueRole": "AwayPlayer",
          "isNationalTeam": false
        }
      ],
      "sortOrder": 120035,
      "tags": [
        "SGP"
      ],
      "metadata": {},
      "milestoneValue": 3
    },
    {
      "id": "0QA320168294#541398240_13L42648Q1-906224463Q20",
      "marketId": "320168294",
      "label": "1\u002B",
      "displayOdds": {
        "american": "\u2212299",
        "decimal": "1.33",
        "fractional": "100/299"
      },
      "trueOdds": 1.33444817,
      "participants": [
        {
          "id": "649606",
          "name": "Keon Ellis",
          "type": "Player",
          "seoIdentifier": "Keon Ellis",
          "statistic": {
            "prefix": "STLPG",
            "value": 1.2
          },
          "venueRole": "HomePlayer",
          "isNationalTeam": false
        }
      ],
      "sortOrder": 13340,
      "tags": [
        "SGP"
      ],
      "metadata": {},
      "milestoneValue": 1
    },
    {
      "id": "0QA320168294#541398280_13L42648Q12102868148Q20",
      "marketId": "320168294",
      "label": "2\u002B",
      "displayOdds": {
        "american": "\u002B153",
        "decimal": "2.53",
        "fractional": "153/100"
      },
      "trueOdds": 2.53,
      "participants": [
        {
          "id": "649606",
          "name": "Keon Ellis",
          "type": "Player",
          "seoIdentifier": "Keon Ellis",
          "statistic": {
            "prefix": "STLPG",
            "value": 1.2
          },
          "venueRole": "HomePlayer",
          "isNationalTeam": false
        }
      ],
      "sortOrder": 25379,
      "tags": [
        "MostBalancedOdds",
        "SGP",
        "MostBalancedGlobalProbability"
      ],
      "metadata": {},
      "milestoneValue": 2
    },
    {
      "id": "0QA320168294#541398319_13L42648Q1847184703Q20",
      "marketId": "320168294",
      "label": "3\u002B",
      "displayOdds": {
        "american": "\u002B510",
        "decimal": "6.10",
        "fractional": "51/10"
      },
      "trueOdds": 6.1,
      "participants": [
        {
          "id": "649606",
          "name": "Keon Ellis",
          "type": "Player",
          "seoIdentifier": "Keon Ellis",
          "statistic": {
            "prefix": "STLPG",
            "value": 1.2
          },
          "venueRole": "HomePlayer",
          "isNationalTeam": false
        }
      ],
      "sortOrder": 61019,
      "tags": [
        "SGP"
      ],
      "metadata": {},
      "milestoneValue": 3
    },
    {
      "id": "0QA320168392#541398495_13L42648Q1-906224463Q20",
      "marketId": "320168392",
      "label": "1\u002B",
      "displayOdds": {
        "american": "\u2212137",
        "decimal": "1.72",
        "fractional": "100/137"
      },
      "trueOdds": 1.72992701,
      "participants": [
        {
          "id": "590986",
          "name": "Evan Mobley",
          "type": "Player",
          "seoIdentifier": "Evan Mobley",
          "statistic": {
            "prefix": "STLPG",
            "value": 0.8
          },
          "venueRole": "HomePlayer",
          "isNationalTeam": false
        }
      ],
      "sortOrder": 17295,
      "tags": [
        "MostBalancedOdds",
        "SGP",
        "MostBalancedGlobalProbability"
      ],
      "metadata": {},
      "milestoneValue": 1
    },
    {
      "id": "0QA320168392#541398511_13L42648Q12102868148Q20",
      "marketId": "320168392",
      "label": "2\u002B",
      "displayOdds": {
        "american": "\u002B356",
        "decimal": "4.56",
        "fractional": "89/25"
      },
      "trueOdds": 4.56,
      "participants": [
        {
          "id": "590986",
          "name": "Evan Mobley",
          "type": "Player",
          "seoIdentifier": "Evan Mobley",
          "statistic": {
            "prefix": "STLPG",
            "value": 0.8
          },
          "venueRole": "HomePlayer",
          "isNationalTeam": false
        }
      ],
      "sortOrder": 45610,
      "tags": [
        "SGP"
      ],
      "metadata": {},
      "milestoneValue": 2
    },
    {
      "id": "0QA320168395#541399681_13L42648Q1-906224463Q20",
      "marketId": "320168395",
      "label": "1\u002B",
      "displayOdds": {
        "american": "\u2212171",
        "decimal": "1.58",
        "fractional": "100/171"
      },
      "trueOdds": 1.58479533,
      "participants": [
        {
          "id": "32992",
          "name": "Dean Wade",
          "type": "Player",
          "seoIdentifier": "Dean Wade",
          "statistic": {
            "prefix": "STLPG",
            "value": 0.8
          },
          "venueRole": "HomePlayer",
          "isNationalTeam": false
        }
      ],
      "sortOrder": 15881,
      "tags": [
        "MostBalancedOdds",
        "SGP",
        "MostBalancedGlobalProbability"
      ],
      "metadata": {},
      "milestoneValue": 1
    },
    {
      "id": "0QA320168395#541399715_13L42648Q12102868148Q20",
      "marketId": "320168395",
      "label": "2\u002B",
      "displayOdds": {
        "american": "\u002B277",
        "decimal": "3.77",
        "fractional": "277/100"
      },
      "trueOdds": 3.77,
      "participants": [
        {
          "id": "32992",
          "name": "Dean Wade",
          "type": "Player",
          "seoIdentifier": "Dean Wade",
          "statistic": {
            "prefix": "STLPG",
            "value": 0.8
          },
          "venueRole": "HomePlayer",
          "isNationalTeam": false
        }
      ],
      "sortOrder": 37715,
      "tags": [
        "SGP"
      ],
      "metadata": {},
      "milestoneValue": 2
    },
    {
      "id": "0QA320168395#541399749_13L42648Q1847184703Q20",
      "marketId": "320168395",
      "label": "3\u002B",
      "displayOdds": {
        "american": "\u002B940",
        "decimal": "10.40",
        "fractional": "47/5"
      },
      "trueOdds": 10.4,
      "participants": [
        {
          "id": "32992",
          "name": "Dean Wade",
          "type": "Player",
          "seoIdentifier": "Dean Wade",
          "statistic": {
            "prefix": "STLPG",
            "value": 0.8
          },
          "venueRole": "HomePlayer",
          "isNationalTeam": false
        }
      ],
      "sortOrder": 104049,
      "tags": [
        "SGP"
      ],
      "metadata": {},
      "milestoneValue": 3
    },
    {
      "id": "0QA320168460#541399705_13L42648Q1-906224463Q20",
      "marketId": "320168460",
      "label": "1\u002B",
      "displayOdds": {
        "american": "\u2212191",
        "decimal": "1.52",
        "fractional": "100/191"
      },
      "trueOdds": 1.52356021,
      "participants": [
        {
          "id": "33144",
          "name": "Jevon Carter",
          "type": "Player",
          "seoIdentifier": "Jevon Carter",
          "statistic": {
            "prefix": "STLPG",
            "value": 0.7
          },
          "venueRole": "AwayPlayer",
          "isNationalTeam": false
        }
      ],
      "sortOrder": 15205,
      "tags": [
        "MostBalancedOdds",
        "SGP",
        "MostBalancedGlobalProbability"
      ],
      "metadata": {},
      "milestoneValue": 1
    },
    {
      "id": "0QA320168460#541399741_13L42648Q12102868148Q20",
      "marketId": "320168460",
      "label": "2\u002B",
      "displayOdds": {
        "american": "\u002B240",
        "decimal": "3.40",
        "fractional": "12/5"
      },
      "trueOdds": 3.4,
      "participants": [
        {
          "id": "33144",
          "name": "Jevon Carter",
          "type": "Player",
          "seoIdentifier": "Jevon Carter",
          "statistic": {
            "prefix": "STLPG",
            "value": 0.7
          },
          "venueRole": "AwayPlayer",
          "isNationalTeam": false
        }
      ],
      "sortOrder": 34041,
      "tags": [
        "SGP"
      ],
      "metadata": {},
      "milestoneValue": 2
    },
    {
      "id": "0QA320168460#541399773_13L42648Q1847184703Q20",
      "marketId": "320168460",
      "label": "3\u002B",
      "displayOdds": {
        "american": "\u002B790",
        "decimal": "8.90",
        "fractional": "79/10"
      },
      "trueOdds": 8.9,
      "participants": [
        {
          "id": "33144",
          "name": "Jevon Carter",
          "type": "Player",
          "seoIdentifier": "Jevon Carter",
          "statistic": {
            "prefix": "STLPG",
            "value": 0.7
          },
          "venueRole": "AwayPlayer",
          "isNationalTeam": false
        }
      ],
      "sortOrder": 89073,
      "tags": [
        "SGP"
      ],
      "metadata": {},
      "milestoneValue": 3
    },
    {
      "id": "0QA320168507#541399132_13L42648Q1-906224463Q20",
      "marketId": "320168507",
      "label": "1\u002B",
      "displayOdds": {
        "american": "\u2212154",
        "decimal": "1.64",
        "fractional": "50/77"
      },
      "trueOdds": 1.64935065,
      "participants": [
        {
          "id": "649544",
          "name": "Paolo Banchero",
          "type": "Player",
          "seoIdentifier": "Paolo Banchero",
          "statistic": {
            "prefix": "STLPG",
            "value": 0.7
          },
          "venueRole": "AwayPlayer",
          "isNationalTeam": false
        }
      ],
      "sortOrder": 16432,
      "tags": [
        "MostBalancedOdds",
        "SGP",
        "MostBalancedGlobalProbability"
      ],
      "metadata": {},
      "milestoneValue": 1
    },
    {
      "id": "0QA320168507#541399227_13L42648Q12102868148Q20",
      "marketId": "320168507",
      "label": "2\u002B",
      "displayOdds": {
        "american": "\u002B305",
        "decimal": "4.05",
        "fractional": "61/20"
      },
      "trueOdds": 4.05,
      "participants": [
        {
          "id": "649544",
          "name": "Paolo Banchero",
          "type": "Player",
          "seoIdentifier": "Paolo Banchero",
          "statistic": {
            "prefix": "STLPG",
            "value": 0.7
          },
          "venueRole": "AwayPlayer",
          "isNationalTeam": false
        }
      ],
      "sortOrder": 40527,
      "tags": [
        "SGP"
      ],
      "metadata": {},
      "milestoneValue": 2
    },
    {
      "id": "0QA320168507#541399311_13L42648Q1847184703Q20",
      "marketId": "320168507",
      "label": "3\u002B",
      "displayOdds": {
        "american": "\u002B1060",
        "decimal": "11.60",
        "fractional": "53/5"
      },
      "trueOdds": 11.6,
      "participants": [
        {
          "id": "649544",
          "name": "Paolo Banchero",
          "type": "Player",
          "seoIdentifier": "Paolo Banchero",
          "statistic": {
            "prefix": "STLPG",
            "value": 0.7
          },
          "venueRole": "AwayPlayer",
          "isNationalTeam": false
        }
      ],
      "sortOrder": 116011,
      "tags": [
        "SGP"
      ],
      "metadata": {},
      "milestoneValue": 3
    },
    {
      "id": "0QA320168564#541400036_13L42648Q1-906224463Q20",
      "marketId": "320168564",
      "label": "1\u002B",
      "displayOdds": {
        "american": "\u2212213",
        "decimal": "1.46",
        "fractional": "100/213"
      },
      "trueOdds": 1.46948357,
      "participants": [
        {
          "id": "800378",
          "name": "Tristan da Silva",
          "type": "Player",
          "seoIdentifier": "Tristan da Silva",
          "statistic": {
            "prefix": "STLPG",
            "value": 0.9
          },
          "venueRole": "AwayPlayer",
          "isNationalTeam": false
        }
      ],
      "sortOrder": 14636,
      "tags": [
        "MostBalancedOdds",
        "SGP",
        "MostBalancedGlobalProbability"
      ],
      "metadata": {},
      "milestoneValue": 1
    },
    {
      "id": "0QA320168564#541400038_13L42648Q12102868148Q20",
      "marketId": "320168564",
      "label": "2\u002B",
      "displayOdds": {
        "american": "\u002B214",
        "decimal": "3.14",
        "fractional": "107/50"
      },
      "trueOdds": 3.14,
      "participants": [
        {
          "id": "800378",
          "name": "Tristan da Silva",
          "type": "Player",
          "seoIdentifier": "Tristan da Silva",
          "statistic": {
            "prefix": "STLPG",
            "value": 0.9
          },
          "venueRole": "AwayPlayer",
          "isNationalTeam": false
        }
      ],
      "sortOrder": 31438,
      "tags": [
        "SGP"
      ],
      "metadata": {},
      "milestoneValue": 2
    },
    {
      "id": "0QA320168564#541400039_13L42648Q1847184703Q20",
      "marketId": "320168564",
      "label": "3\u002B",
      "displayOdds": {
        "american": "\u002B730",
        "decimal": "8.30",
        "fractional": "73/10"
      },
      "trueOdds": 8.3,
      "participants": [
        {
          "id": "800378",
          "name": "Tristan da Silva",
          "type": "Player",
          "seoIdentifier": "Tristan da Silva",
          "statistic": {
            "prefix": "STLPG",
            "value": 0.9
          },
          "venueRole": "AwayPlayer",
          "isNationalTeam": false
        }
      ],
      "sortOrder": 83039,
      "tags": [
        "SGP"
      ],
      "metadata": {},
      "milestoneValue": 3
    }
  ],
  "subscriptionPartials": {
    "markets-230772663": {
      "entity": "markets",
      "query": "$filter=eventId eq \u002733858679\u0027 AND clientMetadata/subCategoryId eq \u002716485\u0027 AND tags/all(t: t ne \u0027SportcastBetBuilder\u0027)",
      "locale": "en"
    }
  }
}